Metadata-Version: 2.1
Name: mlrun-connect
Version: 2021.9.0
Summary: Utilities for connection mlrun to cloud services
Home-page: https://github.com/hayesgb/mlrun_connect/
Maintainer: Greg Hayes
License: Apache 2.0
Keywords: mlrun,iguazio,nuclio,azure
Platform: UNKNOWN
Classifier: Intended Audience :: Developers
Classifier: License :: OSI Approved :: Apache Software License
Classifier: Programming Language :: Python :: 3.7
Classifier: Programming Language :: Python :: 3.8
Classifier: Programming Language :: Python :: 3.9
Classifier: Topic :: Scientific/Engineering
Requires-Python: >3.6
